MANIFEST.in
setup.py
linkbot_jig_programmer/__init__.py
linkbot_jig_programmer/linkbot_jig_programmer.py
linkbot_jig_programmer/mainwindow.py
linkbot_jig_programmer.egg-info/PKG-INFO
linkbot_jig_programmer.egg-info/SOURCES.txt
linkbot_jig_programmer.egg-info/dependency_links.txt
linkbot_jig_programmer.egg-info/entry_points.txt
linkbot_jig_programmer.egg-info/not-zip-safe
linkbot_jig_programmer.egg-info/requires.txt
linkbot_jig_programmer.egg-info/top_level.txt
linkbot_jig_programmer/bootloader/ATmegaBOOT_168_mega128rfa1_8MHz.hex
linkbot_jig_programmer/bootloader/eeprom_out.hex
linkbot_jig_programmer/hexfiles/v4.4.13.4.eeprom
linkbot_jig_programmer/hexfiles/v4.4.13.4.hex